README.md
setup.py
Valifor.egg-info/PKG-INFO
Valifor.egg-info/SOURCES.txt
Valifor.egg-info/dependency_links.txt
Valifor.egg-info/requires.txt
Valifor.egg-info/top_level.txt
scripts/valifor
validators/__init__.py
validators/abstract_validator.py
validators/fasta_validator.py
validators/fastq_validator.py
validators/validator_factory.py