Metadata-Version: 1.0
Name: Valifor
Version: 1.0.0
Summary: A small validator for formats in the NCBI context
Home-page: https://github.com/qbicsoftware/dmqb-grp1-2018
Author: Najia Ahmadi and Alexander Ott
Author-email: a.ott@student.uni-tuebingen.de
License: MIT License
